measure_speaker/__init__.py
measure_speaker/__main__.py
measure_speaker/cli.py
measure_speaker/measure.py
measure_spkr-0.0.3.dist-info/AUTHORS.rst
measure_spkr-0.0.3.dist-info/LICENSE
measure_spkr-0.0.3.dist-info/METADATA
measure_spkr-0.0.3.dist-info/WHEEL
measure_spkr-0.0.3.dist-info/entry_points.txt
measure_spkr-0.0.3.dist-info/top_level.txt
measure_spkr-0.0.3.dist-info/RECORD
