Metadata-Version: 2.1
Name: measure-spkr
Version: 0.0.3
Summary: An app for measuring impulse-frequency response of speaker
Home-page: https://github.com/nnanos/measure_speaker
Author: Nanos Nikolaos
Author-email: nnanos@ceid.upatras.gr
License: MIT
Project-URL: Documentation, https://measure_speaker.readthedocs.io/
Project-URL: Changelog, https://measure_speaker.readthedocs.io/en/latest/changelog.html
Project-URL: Issue Tracker, https://github.com/nnanos/measure_speaker/issues
Platform: UNKNOWN
Classifier: Development Status :: 5 - Production/Stable
Classifier: Intended Audience :: Developers
Classifier: License :: OSI Approved :: MIT License
Classifier: Operating System :: Unix
Classifier: Operating System :: POSIX
Classifier: Operating System :: Microsoft :: Windows
Classifier: Programming Language :: Python
Classifier: Programming Language :: Python :: 3
Classifier: Programming Language :: Python :: 3 :: Only
Classifier: Programming Language :: Python :: 3.6
Classifier: Programming Language :: Python :: 3.7
Classifier: Programming Language :: Python :: 3.8
Classifier: Programming Language :: Python :: 3.9
Classifier: Programming Language :: Python :: Implementation :: CPython
Classifier: Programming Language :: Python :: Implementation :: PyPy
Classifier: Topic :: Utilities
Requires-Python: >=3.8.10
License-File: LICENSE
License-File: AUTHORS.rst
Requires-Dist: numpy
Requires-Dist: librosa
Requires-Dist: matplotlib
Requires-Dist: argparse
Requires-Dist: scipy
Requires-Dist: PySimpleGUI
Requires-Dist: sounddevice
